GoYuyanShengjing/README.md
GoYuyanShengjing/__init__.py
GoYuyanShengjing/__main__.py
GoYuyanShengjing/file.epub
GoYuyanShengjing/index.html
GoYuyanShengjing/css/__init__.py
GoYuyanShengjing/css/annotations.css
GoYuyanShengjing/css/main.css
GoYuyanShengjing/css/normalize.css
GoYuyanShengjing/css/popup.css
GoYuyanShengjing/font/__init__.py
GoYuyanShengjing/font/fontello.eot
GoYuyanShengjing/font/fontello.svg
GoYuyanShengjing/font/fontello.ttf
GoYuyanShengjing/font/fontello.woff
GoYuyanShengjing/img/__init__.py
GoYuyanShengjing/img/annotator-glyph-sprite.png
GoYuyanShengjing/img/annotator-icon-sprite.png
GoYuyanShengjing/img/apple-touch-icon.png
GoYuyanShengjing/img/cancelfullscreen.png
GoYuyanShengjing/img/close.png
GoYuyanShengjing/img/fullscreen.png
GoYuyanShengjing/img/loader.gif
GoYuyanShengjing/img/menu-icon.png
GoYuyanShengjing/img/save.png
GoYuyanShengjing/img/saved.png
GoYuyanShengjing/img/settings-s.png
GoYuyanShengjing/img/settings.png
GoYuyanShengjing/img/star.png
GoYuyanShengjing/js/__init__.py
GoYuyanShengjing/js/epub.js
GoYuyanShengjing/js/epub.min.js
GoYuyanShengjing/js/epub.min.map
GoYuyanShengjing/js/hooks.min.js
GoYuyanShengjing/js/hooks.min.map
GoYuyanShengjing/js/reader.js
GoYuyanShengjing/js/reader.js.map
GoYuyanShengjing/js/reader.min.js
GoYuyanShengjing/js/reader.min.map
GoYuyanShengjing/js/hooks/__init__.py
GoYuyanShengjing/js/hooks/extensions/__init__.py
GoYuyanShengjing/js/hooks/extensions/highlight.js
GoYuyanShengjing/js/libs/__init__.py
GoYuyanShengjing/js/libs/jquery.min.js
GoYuyanShengjing/js/libs/localforage.min.js
GoYuyanShengjing/js/libs/screenfull.js
GoYuyanShengjing/js/libs/screenfull.min.js
GoYuyanShengjing/js/libs/zip.min.js
GoYuyanShengjing/js/plugins/__init__.py
GoYuyanShengjing/js/plugins/hypothesis.js
GoYuyanShengjing/js/plugins/search.js
go_yuyan_shengjing-2024.3.1.0.dist-info/METADATA
go_yuyan_shengjing-2024.3.1.0.dist-info/WHEEL
go_yuyan_shengjing-2024.3.1.0.dist-info/entry_points.txt
go_yuyan_shengjing-2024.3.1.0.dist-info/top_level.txt
go_yuyan_shengjing-2024.3.1.0.dist-info/RECORD
